odoo/addons/pos_payment_entries_globalization/README.rst
odoo/addons/pos_payment_entries_globalization/__init__.py
odoo/addons/pos_payment_entries_globalization/__manifest__.py
odoo/addons/pos_payment_entries_globalization/i18n/ca.po
odoo/addons/pos_payment_entries_globalization/i18n/es.po
odoo/addons/pos_payment_entries_globalization/i18n/pos_payment_entries_globalization.pot
odoo/addons/pos_payment_entries_globalization/models/__init__.py
odoo/addons/pos_payment_entries_globalization/models/account_journal.py
odoo/addons/pos_payment_entries_globalization/models/pos_session.py
odoo/addons/pos_payment_entries_globalization/readme/CONFIGURE.rst
odoo/addons/pos_payment_entries_globalization/readme/CONTRIBUTORS.rst
odoo/addons/pos_payment_entries_globalization/readme/DESCRIPTION.rst
odoo/addons/pos_payment_entries_globalization/readme/USAGE.rst
odoo/addons/pos_payment_entries_globalization/static/description/icon.png
odoo/addons/pos_payment_entries_globalization/static/description/index.html
odoo/addons/pos_payment_entries_globalization/tests/__init__.py
odoo/addons/pos_payment_entries_globalization/tests/test_pos_payment_entries_globalization.py
odoo/addons/pos_payment_entries_globalization/views/account_journal_view.xml
odoo11_addon_pos_payment_entries_globalization-11.0.1.0.1.dist-info/METADATA
odoo11_addon_pos_payment_entries_globalization-11.0.1.0.1.dist-info/WHEEL
odoo11_addon_pos_payment_entries_globalization-11.0.1.0.1.dist-info/top_level.txt
odoo11_addon_pos_payment_entries_globalization-11.0.1.0.1.dist-info/RECORD
